recompose/VERSION
recompose/__init__.py
recompose/cursor.py
recompose/cursors.py
recompose/functions.py
recompose/logging.py
recompose/options.py
recompose/py.typed
recompose/schema_reader.py
recompose/transformer.py
recompose/transformers.py
recompose/types.py
recompose/cursor_classes/__init__.py
recompose/cursor_classes/each_value.py
recompose/cursor_classes/py.typed
recompose/cursor_classes/this_value.py
recompose/enums/__init__.py
recompose/enums/allow.py
recompose/enums/py.typed
recompose/exceptions/__init__.py
recompose/exceptions/invalid_schema.py
recompose/exceptions/no_cursor_for_condition.py
recompose/exceptions/not_a_transformer_type.py
recompose/exceptions/path_not_found.py
recompose/exceptions/recompose.py
recompose/exceptions/unsupported_version.py
recompose/schema_readers/__init__.py
recompose/schema_readers/cursor_schema_reader.py
recompose/schema_readers/path_reader.py
recompose/schema_readers/py.typed
recompose/transformer_classes/__init__.py
recompose/transformer_classes/list_to_object.py
recompose/transformer_classes/pass_through.py
recompose/transformer_classes/py.typed
recompose-1.1.0.dist-info/LICENSE
recompose-1.1.0.dist-info/METADATA
recompose-1.1.0.dist-info/WHEEL
recompose-1.1.0.dist-info/top_level.txt
recompose-1.1.0.dist-info/RECORD
